gcse_images
