Metadata-Version: 1.0
Name: gcse-images
Version: 0.2
Summary: Lightweight utility for using Google Custom Search API for image searches.
Home-page: http://github.com/kjchavez/gcse-images
Author: Kevin Chavez
Author-email: kevin.j.chavez@gmail.com
License: MIT
Platform: UNKNOWN
